tests/__init__.py
tests/test_api.py
tzsmmpay_django/__init__.py
tzsmmpay_django/api.py
tzsmmpay_django/exceptions.py
tzsmmpay_django/utils.py
tzsmmpay_django/version.py
tzsmmpay_django-1.0.0.dist-info/LICENSE
tzsmmpay_django-1.0.0.dist-info/METADATA
tzsmmpay_django-1.0.0.dist-info/WHEEL
tzsmmpay_django-1.0.0.dist-info/top_level.txt
tzsmmpay_django-1.0.0.dist-info/RECORD
